GmdhPy-0.1.1a0.dist-info/DESCRIPTION.rst
GmdhPy-0.1.1a0.dist-info/METADATA
GmdhPy-0.1.1a0.dist-info/RECORD
GmdhPy-0.1.1a0.dist-info/WHEEL
GmdhPy-0.1.1a0.dist-info/metadata.json
GmdhPy-0.1.1a0.dist-info/pbr.json
GmdhPy-0.1.1a0.dist-info/top_level.txt
gmdhpy/__init__.py
gmdhpy/data_preprocessing.py
gmdhpy/gmdh.py
gmdhpy/gmdh_model.py
gmdhpy/plot_gmdh.py
