Metadata-Version: 2.0
Name: GmdhPy
Version: 0.1.1a0
Summary: Multilayered group method of data handling of Machine learning for Python
Home-page: https://github.com/kvoyager/GmdhPy
Author: kvoyager
Author-email: konstantin.kolokolov@gmail.com
License: MIT
Download-URL: https://github.com/kvoyager/GmdhPy/archive/master.zip
Platform: UNKNOWN
Requires-Dist: numpy
Requires-Dist: scikit-learn
Requires-Dist: six
Provides-Extra: graphviz
Requires-Dist: graphviz; extra == 'graphviz'
Requires-Dist: matplotlib; extra == 'graphviz'
